{
  "_class": "group",
  "do_objectID": "64DE6E30-5E7E-478C-9415-93CD04C12D28",
  "exportOptions": {
    "_class": "exportOptions",
    "exportFormats": [
    ],
    "includedLayerIds": [
    ],
    "layerOptions": 0,
    "shouldTrim": false
  },
  "frame": {
    "_class": "rect",
    "constrainProportions": false,
    "height": 44,
    "width": 120,
    "x": 35,
    "y": 296
  },
  "hasClickThrough": false,
  "isFlippedHorizontal": false,
  "isFlippedVertical": false,
  "isLocked": false,
  "isVisible": true,
  "layerListExpandedType": 0,
  "layers": [
    {
      "class": "shapeGroup",
      "id": "D3D58DF3-5D11-4D16-8DC2-363DE2568F0A"
    },
    {
      "class": "text",
      "id": "9AD69F32-1001-4E89-872B-859F639C961C"
    }
  ],
  "name": "按钮",
  "nameIsFixed": true,
  "resizingConstraint": 63,
  "resizingType": 0,
  "rotation": 0,
  "shouldBreakMaskChain": false,
  "style": {
    "sharedObjectID": "165A10A9-708D-4965-B48A-A1B1CBB2416F"
  }
}