{
  "_class": "shapePath",
  "booleanOperation": -1,
  "do_objectID": "E8F9B9C2-20EB-45B2-A673-0283316BDC63",
  "edited": true,
  "exportOptions": {
    "_class": "exportOptions",
    "exportFormats": [
    ],
    "includedLayerIds": [
    ],
    "layerOptions": 0,
    "shouldTrim": false
  },
  "frame": {
    "_class": "rect",
    "constrainProportions": false,
    "height": 1.619999999999993,
    "width": 1.345794392523363,
    "x": 0,
    "y": 0
  },
  "isFlippedHorizontal": false,
  "isFlippedVertical": false,
  "isLocked": false,
  "isVisible": true,
  "layerListExpandedType": 0,
  "name": "Path",
  "nameIsFixed": false,
  "path": {
    "_class": "path",
    "isClosed": true,
    "pointRadiusBehaviour": 1,
    "points": [
      {
        "_class": "curvePoint",
        "cornerRadius": 0,
        "curveFrom": "{0.35555555555555429, 0.018518518518522806}",
        "curveMode": 4,
        "curveTo": "{0.044444444444445078, 0.31481481481481405}",
        "hasCurveFrom": true,
        "hasCurveTo": true,
        "point": "{0.066666666666666041, 0}"
      },
      {
        "_class": "curvePoint",
        "cornerRadius": 0,
        "curveFrom": "{0.95555555555555494, 0.3703703703703719}",
        "curveMode": 4,
        "curveTo": "{0.6444444444444426, 0.037037037037035085}",
        "hasCurveFrom": true,
        "hasCurveTo": true,
        "point": "{0.93333333333333401, 0.07407407407407017}"
      },
      {
        "_class": "curvePoint",
        "cornerRadius": 0,
        "curveFrom": "{0.66666666666666663, 0.98148148148147718}",
        "curveMode": 4,
        "curveTo": "{0.97777777777777908, 0.68518518518518601}",
        "hasCurveFrom": true,
        "hasCurveTo": true,
        "point": "{1, 1}"
      },
      {
        "_class": "curvePoint",
        "cornerRadius": 0,
        "curveFrom": "{0.022222222222224117, 0.61111111111111582}",
        "curveMode": 4,
        "curveTo": "{0.33333333333333331, 0.94444444444444209}",
        "hasCurveFrom": true,
        "hasCurveTo": true,
        "point": "{0, 0.92592592592592982}"
      }
    ]
  },
  "resizingConstraint": 63,
  "resizingType": 0,
  "rotation": 0,
  "shouldBreakMaskChain": false
}