{
  "_class": "shapeGroup",
  "clippingMaskMode": 0,
  "do_objectID": "A45FB99A-9D43-4777-B5F4-408AFE8DA549",
  "exportOptions": {
    "_class": "exportOptions",
    "exportFormats": [
    ],
    "includedLayerIds": [
    ],
    "layerOptions": 0,
    "shouldTrim": false
  },
  "frame": {
    "_class": "rect",
    "constrainProportions": false,
    "height": 191,
    "width": 360,
    "x": 0,
    "y": 73
  },
  "hasClickThrough": false,
  "hasClippingMask": false,
  "isFlippedHorizontal": false,
  "isFlippedVertical": false,
  "isLocked": false,
  "isVisible": true,
  "layerListExpandedType": 0,
  "layers": [
    {
      "class": "rectangle",
      "id": "ADA3A1FB-B662-439C-A8C3-F6847E49005E"
    }
  ],
  "name": "Rectangle 11",
  "nameIsFixed": false,
  "resizingConstraint": 63,
  "resizingType": 0,
  "rotation": 0,
  "shouldBreakMaskChain": false,
  "style": {
    "sharedObjectID": "04177733-13E6-4435-B44F-F8A8C564BA24"
  },
  "windingRule": 1
}