{
  "_class": "shapeGroup",
  "clippingMaskMode": 0,
  "do_objectID": "90E42371-DB0F-41C6-8751-679A647E9C15",
  "exportOptions": {
    "_class": "exportOptions",
    "exportFormats": [
    ],
    "includedLayerIds": [
    ],
    "layerOptions": 0,
    "shouldTrim": false
  },
  "frame": {
    "_class": "rect",
    "constrainProportions": false,
    "height": 2.766962031180401,
    "width": 7.57871855445758,
    "x": 4.88097773062037,
    "y": 2.155020329621381
  },
  "hasClickThrough": false,
  "hasClippingMask": false,
  "isFlippedHorizontal": false,
  "isFlippedVertical": false,
  "isLocked": false,
  "isVisible": true,
  "layerListExpandedType": 0,
  "layers": [
    {
      "class": "shapePath",
      "id": "69A08924-14F8-46FB-A329-B6A6EE5991D5"
    },
    {
      "class": "shapePath",
      "id": "5DFC6BF5-2E1E-40C6-AA8A-1EC3E7D55E2A"
    },
    {
      "class": "shapePath",
      "id": "1AE91D35-390E-410C-934E-5CF6086E1D5C"
    },
    {
      "class": "shapePath",
      "id": "3102587C-970D-485F-8918-8AB1286BD2C1"
    }
  ],
  "name": "Shape",
  "nameIsFixed": false,
  "resizingConstraint": 63,
  "resizingType": 0,
  "rotation": 0,
  "shouldBreakMaskChain": false,
  "style": {
    "_class": "style",
    "blur": {
      "_class": "blur",
      "center": "{0.5, 0.5}",
      "isEnabled": true,
      "motionAngle": 0,
      "radius": 4,
      "type": 2
    },
    "endDecorationType": 0,
    "fills": [
      {
        "_class": "fill",
        "color": {
          "_class": "color",
          "alpha": 1,
          "blue": 1,
          "green": 1,
          "red": 1
        },
        "fillType": 0,
        "isEnabled": true,
        "noiseIndex": 0,
        "noiseIntensity": 0,
        "patternFillType": 1,
        "patternTileScale": 1
      }
    ],
    "miterLimit": 10,
    "startDecorationType": 0
  },
  "windingRule": 0
}