{
  "_class": "group",
  "do_objectID": "28C30B71-ADE0-4CE6-AF4C-1D3FCD316F20",
  "exportOptions": {
    "_class": "exportOptions",
    "exportFormats": [
    ],
    "includedLayerIds": [
    ],
    "layerOptions": 0,
    "shouldTrim": false
  },
  "frame": {
    "_class": "rect",
    "constrainProportions": true,
    "height": 60,
    "width": 60,
    "x": 0,
    "y": 0
  },
  "hasClickThrough": false,
  "isFlippedHorizontal": false,
  "isFlippedVertical": false,
  "isLocked": false,
  "isVisible": true,
  "layerListExpandedType": 2,
  "layers": [
    {
      "class": "shapeGroup",
      "id": "D28920A9-8A86-4E11-A1A5-8A6417086351"
    },
    {
      "class": "shapeGroup",
      "id": "33D34DD8-E5B9-4EB1-80F0-1BCCB8574D88"
    }
  ],
  "name": "添加",
  "nameIsFixed": false,
  "originalObjectID": "28C30B71-ADE0-4CE6-AF4C-1D3FCD316F20",
  "resizingConstraint": 63,
  "resizingType": 0,
  "rotation": 0,
  "shouldBreakMaskChain": false,
  "style": {
    "_class": "style",
    "endDecorationType": 0,
    "miterLimit": 10,
    "shadows": [
      {
        "_class": "shadow",
        "blurRadius": 6,
        "color": {
          "_class": "color",
          "alpha": 0.1921705163043478,
          "blue": 0,
          "green": 0,
          "red": 0
        },
        "contextSettings": {
          "_class": "graphicsContextSettings",
          "blendMode": 0,
          "opacity": 1
        },
        "isEnabled": true,
        "offsetX": 0,
        "offsetY": 4,
        "spread": 0
      }
    ],
    "startDecorationType": 0
  }
}