{
  "_class": "shapePath",
  "booleanOperation": -1,
  "do_objectID": "746842ED-04B8-4650-AF44-AFE54BB5B1C0",
  "edited": true,
  "exportOptions": {
    "_class": "exportOptions",
    "exportFormats": [
    ],
    "includedLayerIds": [
    ],
    "layerOptions": 0,
    "shouldTrim": false
  },
  "frame": {
    "_class": "rect",
    "constrainProportions": false,
    "height": 8.999999999999991,
    "width": 14.99999999999999,
    "x": 0,
    "y": 0
  },
  "isFlippedHorizontal": false,
  "isFlippedVertical": false,
  "isLocked": false,
  "isVisible": true,
  "layerListExpandedType": 0,
  "name": "嘴巴-path",
  "nameIsFixed": false,
  "path": {
    "_class": "path",
    "isClosed": true,
    "pointRadiusBehaviour": 1,
    "points": [
      {
        "_class": "curvePoint",
        "cornerRadius": 0,
        "curveFrom": "{0, 0}",
        "curveMode": 4,
        "curveTo": "{0.21008492120495137, 1.4187238106779354}",
        "hasCurveFrom": true,
        "hasCurveTo": true,
        "point": "{0, 0}"
      },
      {
        "_class": "curvePoint",
        "cornerRadius": 0,
        "curveFrom": "{1, 0.91203153931147019}",
        "curveMode": 4,
        "curveTo": "{0.47899150787950512, 1.0423191611509359}",
        "hasCurveFrom": true,
        "hasCurveTo": true,
        "point": "{1, 0.91203153931147019}"
      }
    ]
  },
  "resizingConstraint": 63,
  "resizingType": 0,
  "rotation": 0,
  "shouldBreakMaskChain": false
}