{
  "_class": "shapeGroup",
  "clippingMaskMode": 0,
  "do_objectID": "641BE639-1A2E-4EEA-AB4B-9C00E3806CE3",
  "exportOptions": {
    "_class": "exportOptions",
    "exportFormats": [
    ],
    "includedLayerIds": [
    ],
    "layerOptions": 0,
    "shouldTrim": false
  },
  "frame": {
    "_class": "rect",
    "constrainProportions": false,
    "height": 150,
    "width": 340,
    "x": 10,
    "y": 797
  },
  "hasClickThrough": false,
  "hasClippingMask": false,
  "isFlippedHorizontal": false,
  "isFlippedVertical": false,
  "isLocked": false,
  "isVisible": true,
  "layerListExpandedType": 0,
  "layers": [
    {
      "class": "rectangle",
      "id": "FCBD3672-559A-4ACD-BFB4-18FED48A2E1A"
    }
  ],
  "name": "Rectangle 25 Copy",
  "nameIsFixed": false,
  "resizingConstraint": 63,
  "resizingType": 0,
  "rotation": 0,
  "shouldBreakMaskChain": false,
  "style": {
    "sharedObjectID": "04177733-13E6-4435-B44F-F8A8C564BA24"
  },
  "windingRule": 1
}