{
  "_class": "shapeGroup",
  "clippingMaskMode": 0,
  "do_objectID": "9F29D009-B74D-472F-821F-0B8E2EE0B337",
  "exportOptions": {
    "_class": "exportOptions",
    "exportFormats": [
    ],
    "includedLayerIds": [
    ],
    "layerOptions": 0,
    "shouldTrim": false
  },
  "frame": {
    "_class": "rect",
    "constrainProportions": false,
    "height": 56,
    "width": 344,
    "x": 0,
    "y": 0
  },
  "hasClickThrough": false,
  "hasClippingMask": false,
  "isFlippedHorizontal": false,
  "isFlippedVertical": false,
  "isLocked": false,
  "isVisible": true,
  "layerListExpandedType": 0,
  "layers": [
    {
      "class": "rectangle",
      "id": "872B4917-FB94-4FAA-BD3C-097A7E78C6D0"
    }
  ],
  "name": "row bounds",
  "nameIsFixed": true,
  "resizingConstraint": 63,
  "resizingType": 0,
  "rotation": 0,
  "shouldBreakMaskChain": false,
  "style": {
    "sharedObjectID": "44FFE068-ED21-4905-805E-205DA4606DF2"
  },
  "windingRule": 1
}